cctop/CCTop.py
cctop/__init__.py
cctop/bedInterval.py
cctop/gff2bedFiles.py
cctop/offTarget.py
cctop/pam.py
cctop/scoreCRISPRater.py
cctop/sequenceMethods.py
cctop/sgRNAbindingSites.py
CCTop-1.0.1.dist-info/LICENSE
CCTop-1.0.1.dist-info/METADATA
CCTop-1.0.1.dist-info/WHEEL
CCTop-1.0.1.dist-info/entry_points.txt
CCTop-1.0.1.dist-info/top_level.txt
CCTop-1.0.1.dist-info/RECORD
