Metadata-Version: 2.1
Name: CCTop
Version: 1.0.1
Summary: CRISPR/Cas Target online predictor
Home-page: https://bitbucket.org/juanlmateo/cctop_standalone
Author: Juan L. Mateo
Author-email: mateojuan@uniovi.es
License: UNKNOWN
Keywords: CRISPR
Platform: UNKNOWN
Classifier: Environment :: Console
Classifier: Intended Audience :: Science/Research
Classifier: License :: OSI Approved :: MIT License
Requires-Python: >=3.5
Provides-Extra: bx
Requires-Dist: bx-python ; extra == 'bx'
